{
    "exchange-documents": {
        "exchange-document": {
            "bibliographic-data": {
                "publication-reference": {
                    "document-id": [
                        {
                            "country": "CN",
                            "doc-number": "116429545",
                            "kind": "A",
                            "date": "20230714"
                        },
                        {
                            "doc-number": "CN116429545",
                            "date": "20230714"
                        }
                    ]
                },
                "classifications-ipcr": {
                    "classification-ipcr": [
                        {
                            "text": "C23F   1/    28            A I                    "
                        },
                        {
                            "text": "G01N   1/    32            A I                    "
                        },
                        {
                            "text": "G01N  21/    84            A I                    "
                        }
                    ]
                },
                "patent-classifications": {
                    "patent-classification": [
                        {
                            "classification-scheme": null,
                            "section": "C",
                            "class": "23",
                            "subclass": "F",
                            "main-group": "1",
                            "subgroup": "28",
                            "classification-value": "I",
                            "generating-office": "CN"
                        },
                        {
                            "classification-scheme": null,
                            "section": "G",
                            "class": "01",
                            "subclass": "N",
                            "main-group": "1",
                            "subgroup": "32",
                            "classification-value": "I",
                            "generating-office": "CN"
                        },
                        {
                            "classification-scheme": null,
                            "section": "G",
                            "class": "01",
                            "subclass": "N",
                            "main-group": "21",
                            "subgroup": "84",
                            "classification-value": "I",
                            "generating-office": "CN"
                        }
                    ]
                },
                "application-reference": {
                    "document-id": [
                        {
                            "country": "CN",
                            "doc-number": "202310466409",
                            "kind": "A"
                        },
                        {
                            "doc-number": "CN202310466409",
                            "date": "20230427"
                        },
                        {
                            "doc-number": "202310466409.1"
                        }
                    ]
                },
                "priority-claims": {
                    "priority-claim": {
                        "document-id": {
                            "doc-number": "CN202310466409",
                            "date": "20230427"
                        }
                    }
                },
                "parties": {
                    "applicants": {
                        "applicant": [
                            {
                                "applicant-name": {
                                    "name": "CHENGDU HAIRUI PRODUCT QUALITY TECH TESTING CO LTD"
                                }
                            },
                            {
                                "applicant-name": {
                                    "name": "成都市海瑞产品质量技术检测有限公司"
                                }
                            }
                        ]
                    },
                    "inventors": {
                        "inventor": [
                            {
                                "inventor-name": {
                                    "name": "HUANG ZHENYONG"
                                }
                            },
                            {
                                "inventor-name": {
                                    "name": " DONG JINYUAN"
                                }
                            },
                            {
                                "inventor-name": {
                                    "name": "黄振勇, "
                                }
                            },
                            {
                                "inventor-name": {
                                    "name": "董金元"
                                }
                            }
                        ]
                    }
                },
                "invention-title": [
                    "1Cr11Ni2W2MoV metallographic corrosion formula as well as preparation method and use method of 1Cr11Ni2W2MoV metallographic corrosion formula",
                    "1Cr11Ni2W2MoV金相腐蚀配方及其配置方法、使用方法"
                ]
            },
            "abstract": [
                {
                    "p": "The invention discloses a 1Cr11Ni2W2MoV metallographic corrosion formula as well as a preparation method and a use method thereof, and relates to the technical field of metallographic sample detection, and the 1Cr11Ni2W2MoV metallographic corrosion formula comprises ferric trichloride, copper chloride, hydrogen chloride, water, glacial acetic acid and neogilde. Wherein the ferric trichloride accounts for 20-25 g, the copper chloride accounts for 10-15 g, the hydrogen chloride accounts for 40-50 ml, the water accounts for 145-150 ml, the glacial acetic acid accounts for 5-10 ml, and the new gilgil accounts for 3-5 drops. The optimal formula is as follows: 24 g of ferric trichloride, 12 g of copper chloride, 45 ml of hydrogen chloride, 150 ml of water, 7 ml of glacial acetic acid and 5 drops of neogilgil. According to the method, the combined action of ferric trichloride and copper chloride in GB/T13298-2015 is comprehensively utilized, and hydrochloric acid is added with glacial acetic acid and new Jiergil, so that tissues and crystal grains can be clearly displayed, accurate rating can be realized, and a metallograph can be provided, so that the existing requirements can be met, and the method is good in reproducibility, high in detection efficiency and low in cost. And the method is suitable for various Cr11 type and Cr13 type low-carbon martensitic stainless steel and is high in universality."
                },
                {
                    "p": "本发明公开了1Cr11Ni2W2MoV金相腐蚀配方及其配置方法、使用方法，涉及到金相试样检测技术领域，1Cr11Ni2W2MoV金相腐蚀配方，包括三氯化铁，氯化铜，氯化氢，水，冰醋酸以及新吉尔灭。其中，所述三氯化铁20‑25g，氯化铜10‑15g，氯化氢40‑50ml，水145‑150ml，冰醋酸5‑10ml以及新吉尔灭3‑5滴。而最优配方为：所述三氯化铁24g，氯化铜12g，氯化氢45ml，水150ml，冰醋酸7ml以及新吉尔灭5滴。本发明通过综合运用GB/T13298‑2015中的三氯化铁和氯化铜的共同作用，配以盐酸新增冰醋酸、新吉尔灭，使得组织和晶粒都能清晰显示，能准确评级并提供金相照片，从而能够满足现有需求，且该方法重现性好，检测效率高，适用于多种Cr11型、Cr13型低碳马氏体不锈钢，通用性强。"
                }
            ]
        }
    }
}