{
    "exchange-documents": {
        "exchange-document": {
            "bibliographic-data": {
                "publication-reference": {
                    "document-id": [
                        {
                            "country": "CN",
                            "doc-number": "118147784",
                            "kind": "A",
                            "date": "20240607"
                        },
                        {
                            "doc-number": "CN118147784",
                            "date": "20240607"
                        }
                    ]
                },
                "classifications-ipcr": {
                    "classification-ipcr": [
                        {
                            "text": "D01D   5/    06            A I                    "
                        },
                        {
                            "text": "D01D   5/    34            A I                    "
                        },
                        {
                            "text": "D01F   1/    10            A I                    "
                        },
                        {
                            "text": "D01F   8/    02            A I                    "
                        },
                        {
                            "text": "D01F   8/    16            A I                    "
                        }
                    ]
                },
                "patent-classifications": {
                    "patent-classification": [
                        {
                            "classification-scheme": null,
                            "section": "D",
                            "class": "01",
                            "subclass": "D",
                            "main-group": "5",
                            "subgroup": "06",
                            "classification-value": "I",
                            "generating-office": "CN"
                        },
                        {
                            "classification-scheme": null,
                            "section": "D",
                            "class": "01",
                            "subclass": "D",
                            "main-group": "5",
                            "subgroup": "34",
                            "classification-value": "I",
                            "generating-office": "CN"
                        },
                        {
                            "classification-scheme": null,
                            "section": "D",
                            "class": "01",
                            "subclass": "F",
                            "main-group": "1",
                            "subgroup": "10",
                            "classification-value": "I",
                            "generating-office": "CN"
                        },
                        {
                            "classification-scheme": null,
                            "section": "D",
                            "class": "01",
                            "subclass": "F",
                            "main-group": "8",
                            "subgroup": "02",
                            "classification-value": "I",
                            "generating-office": "CN"
                        },
                        {
                            "classification-scheme": null,
                            "section": "D",
                            "class": "01",
                            "subclass": "F",
                            "main-group": "8",
                            "subgroup": "16",
                            "classification-value": "I",
                            "generating-office": "CN"
                        }
                    ]
                },
                "application-reference": {
                    "document-id": [
                        {
                            "country": "CN",
                            "doc-number": "202410411152",
                            "kind": "A"
                        },
                        {
                            "doc-number": "CN202410411152",
                            "date": "20240408"
                        },
                        {
                            "doc-number": "202410411152.4"
                        }
                    ]
                },
                "priority-claims": {
                    "priority-claim": {
                        "document-id": {
                            "doc-number": "CN202410411152",
                            "date": "20240408"
                        }
                    }
                },
                "parties": {
                    "applicants": {
                        "applicant": [
                            {
                                "applicant-name": {
                                    "name": "UNIV SHANGHAI ENG SCIENCE"
                                }
                            },
                            {
                                "applicant-name": {
                                    "name": "上海工程技术大学"
                                }
                            }
                        ]
                    },
                    "inventors": {
                        "inventor": [
                            {
                                "inventor-name": {
                                    "name": "ZHAO HONG"
                                }
                            },
                            {
                                "inventor-name": {
                                    "name": " XU LIHUI"
                                }
                            },
                            {
                                "inventor-name": {
                                    "name": " CAI ZAISHENG"
                                }
                            },
                            {
                                "inventor-name": {
                                    "name": " HU JINGUANG"
                                }
                            },
                            {
                                "inventor-name": {
                                    "name": " ZHOU MAN"
                                }
                            },
                            {
                                "inventor-name": {
                                    "name": " PAN HONG"
                                }
                            },
                            {
                                "inventor-name": {
                                    "name": " YAO CHENGJIAN"
                                }
                            },
                            {
                                "inventor-name": {
                                    "name": " LI YONGHE"
                                }
                            },
                            {
                                "inventor-name": {
                                    "name": " YANG QUN"
                                }
                            },
                            {
                                "inventor-name": {
                                    "name": "赵红, "
                                }
                            },
                            {
                                "inventor-name": {
                                    "name": "徐丽慧, "
                                }
                            },
                            {
                                "inventor-name": {
                                    "name": "蔡再生, "
                                }
                            },
                            {
                                "inventor-name": {
                                    "name": "胡劲光, "
                                }
                            },
                            {
                                "inventor-name": {
                                    "name": "周曼, "
                                }
                            },
                            {
                                "inventor-name": {
                                    "name": "潘虹, "
                                }
                            },
                            {
                                "inventor-name": {
                                    "name": "姚程健, "
                                }
                            },
                            {
                                "inventor-name": {
                                    "name": "李永贺, "
                                }
                            },
                            {
                                "inventor-name": {
                                    "name": "杨群"
                                }
                            }
                        ]
                    }
                },
                "invention-title": [
                    "Preparation method of photoresponse type conductive regenerated cellulose fiber",
                    "一种光响应型导电再生纤维素纤维的制备方法"
                ]
            },
            "abstract": [
                {
                    "p": "The invention relates to a preparation method of a photoresponse type conductive regenerated cellulose fiber, which comprises the following steps: mixing pyrrole and a cellulose solution to prepare a spinning solution, extruding the spinning solution into a C3N4 aqueous dispersion coagulating bath, dropwise adding an oxidant into the coagulating bath at the speed of 0.05-1mL/min, and realizing oxidative polymerization of pyrrole in the spinning forming process to obtain the photoresponse type conductive regenerated cellulose fiber. The light response type conductive regenerated cellulose fiber is prepared. According to the preparation method of the photoresponse type conductive regenerated cellulose fiber, a pyrrole conductive polymer monomer and a cellulose solution are mixed to prepare a spinning solution, a cellulose chain in the cellulose solution and the monomer can generate a large number of hydrogen bond networks, the spinning solution is squeezed into a C3N4 aqueous dispersion, in-situ compounding of polypyrrole (PPy) and C3N4 is achieved, and the photoresponse type conductive regenerated cellulose fiber is obtained. The binding strength of the obtained conductive regenerated cellulose fiber is superior to that of a conductive polymer/cellulose fiber prepared by a traditional method, and the conductive regenerated cellulose fiber has excellent mechanical performance, visible light enhanced antibacterial performance and energy storage performance."
                },
                {
                    "p": "本发明涉及一种光响应型导电再生纤维素纤维的制备方法，将吡咯与纤维素溶液混合后配制得到纺丝液，将纺丝液挤入C3N4水分散液凝固浴中，然后以0.05～1mL/min的速度向凝固浴中滴加氧化剂，在纺丝成形的过程中实现吡咯的氧化聚合，制得光响应型导电再生纤维素纤维。本发明的一种光响应型导电再生纤维素纤维的制备方法，将吡咯导电聚合物单体与纤维素溶液混合制得纺丝液，纤维素溶液中的纤维素链能与单体产生大量氢键网络，纺丝液挤入C3N4水分散液，实现聚吡咯(PPy)和C3N4的原位复合，得到的导电再生纤维素纤维结合牢度优于传统方法制备的导电聚合物/纤维素纤维，兼具优良的机械性能、可见光增强抗菌及储能性能。"
                }
            ]
        }
    }
}