{
    "exchange-documents": {
        "exchange-document": {
            "bibliographic-data": {
                "publication-reference": {
                    "document-id": [
                        {
                            "country": "CN",
                            "doc-number": "116422356",
                            "kind": "A",
                            "date": "20230714"
                        },
                        {
                            "doc-number": "CN116422356",
                            "date": "20230714"
                        }
                    ]
                },
                "classifications-ipcr": {
                    "classification-ipcr": [
                        {
                            "text": "B01J  27/    24            A I                    "
                        },
                        {
                            "text": "B01J  37/    08            A I                    "
                        },
                        {
                            "text": "C01B   3/    04            A I                    "
                        }
                    ]
                },
                "patent-classifications": {
                    "patent-classification": [
                        {
                            "classification-scheme": null,
                            "section": "B",
                            "class": "01",
                            "subclass": "J",
                            "main-group": "21",
                            "subgroup": "063",
                            "classification-value": "I",
                            "generating-office": "CN"
                        },
                        {
                            "classification-scheme": null,
                            "section": "B",
                            "class": "01",
                            "subclass": "J",
                            "main-group": "27",
                            "subgroup": "24",
                            "classification-value": "I",
                            "generating-office": "CN"
                        },
                        {
                            "classification-scheme": null,
                            "section": "B",
                            "class": "01",
                            "subclass": "J",
                            "main-group": "35",
                            "subgroup": "39",
                            "classification-value": "I",
                            "generating-office": "CN"
                        },
                        {
                            "classification-scheme": null,
                            "section": "B",
                            "class": "01",
                            "subclass": "J",
                            "main-group": "37",
                            "subgroup": "086",
                            "classification-value": "I",
                            "generating-office": "CN"
                        },
                        {
                            "classification-scheme": null,
                            "section": "C",
                            "class": "01",
                            "subclass": "B",
                            "main-group": "3",
                            "subgroup": "042",
                            "classification-value": "I",
                            "generating-office": "CN"
                        },
                        {
                            "classification-scheme": null,
                            "section": "Y",
                            "class": "02",
                            "subclass": "E",
                            "main-group": "60",
                            "subgroup": "36",
                            "classification-value": "A",
                            "generating-office": "EP"
                        }
                    ]
                },
                "application-reference": {
                    "document-id": [
                        {
                            "country": "CN",
                            "doc-number": "202310209365",
                            "kind": "A"
                        },
                        {
                            "doc-number": "CN202310209365",
                            "date": "20230306"
                        },
                        {
                            "doc-number": "202310209365.4"
                        }
                    ]
                },
                "priority-claims": {
                    "priority-claim": {
                        "document-id": {
                            "doc-number": "CN202310209365",
                            "date": "20230306"
                        }
                    }
                },
                "parties": {
                    "applicants": {
                        "applicant": [
                            {
                                "applicant-name": {
                                    "name": "UNIV ZHAOQING"
                                }
                            },
                            {
                                "applicant-name": {
                                    "name": " UNIV WUHAN"
                                }
                            },
                            {
                                "applicant-name": {
                                    "name": " ZHAOQING WANWEI NEW MATERIAL TECH CO LTD"
                                }
                            },
                            {
                                "applicant-name": {
                                    "name": "肇庆学院, "
                                }
                            },
                            {
                                "applicant-name": {
                                    "name": "武汉大学, "
                                }
                            },
                            {
                                "applicant-name": {
                                    "name": "肇庆市万维新材料科技有限公司"
                                }
                            }
                        ]
                    },
                    "inventors": {
                        "inventor": [
                            {
                                "inventor-name": {
                                    "name": "ZENG PENG"
                                }
                            },
                            {
                                "inventor-name": {
                                    "name": " PENG TIANYOU"
                                }
                            },
                            {
                                "inventor-name": {
                                    "name": " JIA HUAIYANG"
                                }
                            },
                            {
                                "inventor-name": {
                                    "name": " LIANG CUIEN"
                                }
                            },
                            {
                                "inventor-name": {
                                    "name": " WANG SHAOCHUAN"
                                }
                            },
                            {
                                "inventor-name": {
                                    "name": "曾鹏, "
                                }
                            },
                            {
                                "inventor-name": {
                                    "name": "彭天右, "
                                }
                            },
                            {
                                "inventor-name": {
                                    "name": "贾怀杨, "
                                }
                            },
                            {
                                "inventor-name": {
                                    "name": "梁翠恩, "
                                }
                            },
                            {
                                "inventor-name": {
                                    "name": "王绍川"
                                }
                            }
                        ]
                    }
                },
                "invention-title": [
                    "CuNx cluster modified TiO2 composite material, in-situ preparation method and photocatalytic application thereof",
                    "一种CuNx团簇修饰TiO2复合材料、原位制备方法及其光催化应用"
                ],
                "references-cited": {
                    "citation": [
                        {
                            "patcit": {
                                "document-id": [
                                    {
                                        "doc-number": "JP2013126653",
                                        "name": "SUMITOMO CHEMICAL CO, et al",
                                        "date": "20130627"
                                    },
                                    {
                                        "country": "JP",
                                        "doc-number": "2013126653",
                                        "kind": "A",
                                        "name": "SUMITOMO CHEMICAL CO, et al",
                                        "date": "20130627"
                                    }
                                ]
                            },
                            "category": "A"
                        },
                        {
                            "patcit": {
                                "document-id": [
                                    {
                                        "doc-number": "US2016009621",
                                        "name": "BLAIR RICHARD [US]",
                                        "date": "20160114"
                                    },
                                    {
                                        "country": "US",
                                        "doc-number": "2016009621",
                                        "kind": "A1",
                                        "name": "BLAIR RICHARD [US]",
                                        "date": "20160114"
                                    }
                                ]
                            },
                            "category": "A"
                        },
                        {
                            "patcit": {
                                "document-id": [
                                    {
                                        "doc-number": "CN107715904",
                                        "name": "UNIV HUAZHONG AGRICULTURAL, et al",
                                        "date": "20180223"
                                    },
                                    {
                                        "country": "CN",
                                        "doc-number": "107715904",
                                        "kind": "A",
                                        "name": "UNIV HUAZHONG AGRICULTURAL, et al",
                                        "date": "20180223"
                                    }
                                ]
                            },
                            "category": "A"
                        },
                        {
                            "patcit": {
                                "document-id": [
                                    {
                                        "doc-number": "US2018274013",
                                        "name": "ZHANG HUA [SG], et al",
                                        "date": "20180927"
                                    },
                                    {
                                        "country": "US",
                                        "doc-number": "2018274013",
                                        "kind": "A1",
                                        "name": "ZHANG HUA [SG], et al",
                                        "date": "20180927"
                                    }
                                ]
                            },
                            "category": "A"
                        },
                        {
                            "patcit": {
                                "document-id": [
                                    {
                                        "doc-number": "CN108620136",
                                        "name": "UNIV NORTHWEST NORMAL",
                                        "date": "20181009"
                                    },
                                    {
                                        "country": "CN",
                                        "doc-number": "108620136",
                                        "kind": "A",
                                        "name": "UNIV NORTHWEST NORMAL",
                                        "date": "20181009"
                                    }
                                ]
                            },
                            "category": "A"
                        },
                        {
                            "patcit": {
                                "document-id": [
                                    {
                                        "doc-number": "CN109225331",
                                        "name": "UNIV CHINA PETROLEUM EAST CHINA",
                                        "date": "20190118"
                                    },
                                    {
                                        "country": "CN",
                                        "doc-number": "109225331",
                                        "kind": "A",
                                        "name": "UNIV CHINA PETROLEUM EAST CHINA",
                                        "date": "20190118"
                                    }
                                ]
                            },
                            "category": "A"
                        },
                        {
                            "patcit": {
                                "document-id": [
                                    {
                                        "doc-number": "CN109821579",
                                        "name": "JIN PENGXIA",
                                        "date": "20190531"
                                    },
                                    {
                                        "country": "CN",
                                        "doc-number": "109821579",
                                        "kind": "A",
                                        "name": "JIN PENGXIA",
                                        "date": "20190531"
                                    }
                                ]
                            },
                            "category": "A"
                        },
                        {
                            "patcit": {
                                "document-id": [
                                    {
                                        "doc-number": "CN110227527",
                                        "name": "UNIV WUHAN",
                                        "date": "20190913"
                                    },
                                    {
                                        "country": "CN",
                                        "doc-number": "110227527",
                                        "kind": "A",
                                        "name": "UNIV WUHAN",
                                        "date": "20190913"
                                    }
                                ]
                            },
                            "category": "A"
                        },
                        {
                            "patcit": {
                                "document-id": [
                                    {
                                        "doc-number": "CN114832861",
                                        "name": "UNIV DALIAN TECH                                                                                    ",
                                        "date": "20220802"
                                    },
                                    {
                                        "country": "CN",
                                        "doc-number": "114832861",
                                        "kind": "A",
                                        "name": "UNIV DALIAN TECH                                                                                    ",
                                        "date": "20220802"
                                    }
                                ]
                            },
                            "category": "A"
                        },
                        {
                            "patcit": {
                                "document-id": [
                                    {
                                        "doc-number": "CN114854034",
                                        "name": "UNIV WUHAN                                                                                          ",
                                        "date": "20220805"
                                    },
                                    {
                                        "country": "CN",
                                        "doc-number": "114854034",
                                        "kind": "A",
                                        "name": "UNIV WUHAN                                                                                          ",
                                        "date": "20220805"
                                    }
                                ]
                            },
                            "category": "A"
                        },
                        {
                            "patcit": {
                                "document-id": [
                                    {
                                        "doc-number": "CN114887661",
                                        "name": "UNIV CHONGQING TECH & BUSINESS                                                                      ",
                                        "date": "20220812"
                                    },
                                    {
                                        "country": "CN",
                                        "doc-number": "114887661",
                                        "kind": "A",
                                        "name": "UNIV CHONGQING TECH & BUSINESS                                                                      ",
                                        "date": "20220812"
                                    }
                                ]
                            },
                            "category": "A"
                        }
                    ]
                }
            },
            "abstract": [
                {
                    "p": "The invention discloses a CuNx cluster modified TiO2 composite material (namely CuNx/TiO2), an in-situ preparation method and photocatalytic application of the CuNx cluster modified TiO2 composite material. According to the tetra (4-pyridyl) porphyrin copper/NH2-MIL-125 (Ti) composite material, 5, 10, 15, 20-tetra (4-pyridyl) porphyrin copper (namely tetra (4-pyridyl) porphyrin copper) with a Cu-N4 structure is implanted into holes of a metal organic framework compound (MOF) (namely NH2-MIL-125 (Ti)-based MOF) constructed by a titanium oxygen cluster and 2-aminoterephthalic acid on the basis of intermolecular hydrogen-bond interaction to prepare the tetra (4-pyridyl) porphyrin copper/NH2-MIL-125 (Ti) composite material, and the tetra (4-pyridyl) porphyrin copper/NH2-MIL-125 (Ti) composite material is used for preparing the tetra (4-pyridyl) porphyrin copper composite material. And then performing thermal decomposition to prepare the CuNx/TiO2 composite material in situ. The CuNx/TiO2 composite material prepared in situ through thermal decomposition of the tetra (4-pyridyl) copper porphyrin/NH2-MIL-125 (Ti) composite material according to the feeding mass ratio of 1: 50 shows the most excellent performance of hydrogen production through photocatalytic decomposition of water, does not need noble metal loading, and has a good application prospect in the field of light energy-hydrogen energy conversion."
                },
                {
                    "p": "本发明公开了一种CuNx团簇修饰TiO2复合材料(即CuNx/TiO2)、原位制备方法及其光催化应用。本发明基于分子间氢键作用将具有Cu‑N4结构的5,10,15,20‑四(4‑吡啶基)卟啉铜(即四(4‑吡啶基)卟啉铜)植入由钛氧团簇和2‑氨基对苯二甲酸构筑的金属有机框架化合物(MOF)(即NH2‑MIL‑125(Ti)基MOF)孔内制备四(4‑吡啶基)卟啉铜/NH2‑MIL‑125(Ti)复合材料，然后热分解原位制备CuNx/TiO2复合材料。其中，投料质量比为1:50的四(4‑吡啶基)卟啉铜/NH2‑MIL‑125(Ti)复合材料热分解原位制备的CuNx/TiO2复合材料表现出最优异的光催化分解水产氢性能，无需贵金属负载，在光能‑氢能转换领域具有良好的应用前景。"
                }
            ]
        }
    }
}